sphinx_gitref/__init__.py
sphinx_gitref/__main__.py
sphinx_gitref/builders.py
sphinx_gitref/commands.py
sphinx_gitref/constants.py
sphinx_gitref/exceptions.py
sphinx_gitref/git.py
sphinx_gitref/hasher.py
sphinx_gitref/parser.py
sphinx_gitref/remote.py
sphinx_gitref/role.py
sphinx_gitref/setup.py
sphinx_gitref-0.4.1.dist-info/LICENSE
sphinx_gitref-0.4.1.dist-info/METADATA
sphinx_gitref-0.4.1.dist-info/WHEEL
sphinx_gitref-0.4.1.dist-info/entry_points.txt
sphinx_gitref-0.4.1.dist-info/top_level.txt
sphinx_gitref-0.4.1.dist-info/RECORD
