Metadata-Version: 2.1
Name: sphinx-gitref
Version: 0.4.1
Summary: Keep your sphinx docs in sync with your code.
Author-email: Richard Terry <code@radiac.net>
Project-URL: Homepage, https://radiac.net/projects/sphinx-gitref/
Project-URL: Documentation, https://sphinx-gitref.readthedocs.io/
Project-URL: Changelog, https://github.com/radiac/sphinx-gitref
Project-URL: Repository, https://github.com/radiac/sphinx-gitref
Project-URL: Issues, https://github.com/radiac/sphinx-gitref/issues
Keywords: django
Classifier: Development Status :: 4 - Beta
Classifier: Framework :: Sphinx :: Extension
Classifier: License :: OSI Approved :: BSD License
Classifier: Programming Language :: Python :: 3
Classifier: Operating System :: OS Independent
Requires-Python: >=3.7
License-File: LICENSE
Requires-Dist: click
Requires-Dist: docutils
Requires-Dist: sphinx
